aws_okta_processor/__init__.py
aws_okta_processor/__main__.py
aws_okta_processor/cli.py
aws_okta_processor/commands/__init__.py
aws_okta_processor/commands/authenticate.py
aws_okta_processor/commands/base.py
aws_okta_processor/commands/getroles.py
aws_okta_processor/core/__init__.py
aws_okta_processor/core/fetcher.py
aws_okta_processor/core/okta.py
aws_okta_processor/core/prompt.py
aws_okta_processor/core/saml.py
aws_okta_processor/core/tty.py
aws_okta_processor-1.10.0.dist-info/LICENSE
aws_okta_processor-1.10.0.dist-info/METADATA
aws_okta_processor-1.10.0.dist-info/WHEEL
aws_okta_processor-1.10.0.dist-info/entry_points.txt
aws_okta_processor-1.10.0.dist-info/RECORD
