Metadata-Version: 2.1
Name: aws-okta-processor
Version: 1.10.0
Summary: Resource for fetching AWS Role credentials from Okta
Home-page: https://github.com/godaddy/aws-okta-processor
Author: Cloud Platform Solutions
Author-email: cp-solutions@godaddy.com
Requires-Python: >=3.9,<4.0
Classifier: Programming Language :: Python :: 3
Classifier: Programming Language :: Python :: 3.9
Classifier: Programming Language :: Python :: 3.10
Classifier: Programming Language :: Python :: 3.11
Classifier: Programming Language :: Python :: 3.12
Requires-Dist: beautifulsoup4 (>=4.11.1)
Requires-Dist: boto3 (>=1.9.134)
Requires-Dist: contextlib2 (>=0.5.5)
Requires-Dist: defusedxml (>=0.7.1)
Requires-Dist: docopt (>=0.6.2)
Requires-Dist: requests (>=2.21.0)
Requires-Dist: six (>=1.12.0)
Requires-Dist: tomlkit (>=0.13.2,<0.14.0)
Project-URL: Repository, https://github.com/godaddy/aws-okta-processor
